tsg_extensions/__init__.py
tsg_extensions/cmd.py
tsg_extensions/cmd_cleanup.py
tsg_extensions/ref_doc.py
tsg_extensions/term.py
tsg_extensions-2021.2.5.dist-info/METADATA
tsg_extensions-2021.2.5.dist-info/WHEEL
tsg_extensions-2021.2.5.dist-info/top_level.txt
tsg_extensions-2021.2.5.dist-info/RECORD
