Metadata-Version: 2.1
Name: tsg-extensions
Version: 2021.2.5
Summary: Markdown extensions
Home-page: UNKNOWN
Author: Nicholas Willhite,
Author-email: nicholas.willhite@dell.com
License: UNKNOWN
Platform: UNKNOWN
Requires-Dist: markdown
